dlc2nwb/__init__.py
dlc2nwb/utils.py
dlc2nwb/version.py
dlc2nwb-0.3.dist-info/LICENSE
dlc2nwb-0.3.dist-info/METADATA
dlc2nwb-0.3.dist-info/WHEEL
dlc2nwb-0.3.dist-info/top_level.txt
dlc2nwb-0.3.dist-info/RECORD
