Metadata-Version: 2.1
Name: dlc2nwb
Version: 0.3
Summary: DeepLabCut <-> NWB conversion utilities
Home-page: https://github.com/DeepLabCut/DLC2NWB
Author: A. & M. Mathis Labs
Author-email: alexander@deeplabcut.org
Project-URL: Bug Tracker, https://github.com/DeepLabCut/DLC2NWB/issues
Classifier: Programming Language :: Python :: 3
Classifier: License :: OSI Approved :: MIT License
Classifier: Operating System :: OS Independent
Requires-Python: >=3.7
License-File: LICENSE
Requires-Dist: ndx-pose (>=0.1.1)
Provides-Extra: test
Requires-Dist: pytest ; extra == 'test'
Requires-Dist: deeplabcut (>=2.2.0.2) ; extra == 'test'
